README.rst
setup.py
PYTHorrent.egg-info/PKG-INFO
PYTHorrent.egg-info/SOURCES.txt
PYTHorrent.egg-info/dependency_links.txt
PYTHorrent.egg-info/requires.txt
PYTHorrent.egg-info/top_level.txt
pythorrent/__init__.py
pythorrent/__main__.py
pythorrent/config.py
pythorrent/peer.py
pythorrent/peer_stores.py
pythorrent/pieces.py
pythorrent/torrent.py