Metadata-Version: 1.0
Name: PYTHorrent
Version: 0.1.0
Summary: A BitTorrent client written entirely in Python so that you can get to the depths of the protocol
Home-page: https://github.com/yamatt/python-pythorrent
Author: Matt Copperwaite
Author-email: mattcopp@gmail.com
License: AGPLv3
Platform: UNKNOWN
